{
  "file_name": "19900017394-ページ-97.pdf",
  "file_hash": "ae55046c99f0f90a2bd2a41aefbc8c29b2cbafa03f4e25ae973f3ce4e638c0da",
  "processed_at": "2025-06-12T16:39:29.224323",
  "pages_content": [
    {
      "page_number": 1,
      "content": "Chapter 4. Capitalization\n. A common noun used with a number or letter for purposes of designation\nis not capitalized (G.P.O. 1984):\nchapter 4\npart I\nfigure 1\nreference 25\ncase 8\nrun 234\n. Only when the word the is part of an official name is it capitalized:\nThe College of William and Mary\nthe National Aeronautics and Space Administration\n4.5.1. Personal Names\nand Titles\nRarely is there any question concerning capitalization of personal names.\n· In foreign names, particles such as d', de, du, and von are capitalized unless\npreceded by a forename or title:\nE. I. du Pont\nDu Pont\nTheodore von Karman Von Karman Institute\n. Remember that a personal name that is used in a common sense is no longer\ncapitalized:\nthe units curie, watt, newton, and kelvin\nBut\ndegree Celsius\ndegree Rankine\ndegree Fahrenheit\n· Civil and professional titles are capitalized when they precede a personal\nname as part of the name (Chicago Press 1982):\nPresident Reagan\nDirector Petersen\nChief Scientist Barnwell\nEngineer-in-Charge Reid\nSuch titles are not capitalized in apposition however:\nthe chief scientist, Richard Barnwell\nthe chief of Materials Division, Darrel Tenney\n· Civil and professional titles following or in place of a personal name are\nrarely capitalized (Chicago Press 1982):\nRichard Petersen, director of Langley Research Center; the director\nA. J. Hansbrough, chief of the Research Information and Applications\nDivision; the division chief\n88",
      "source_file": "19900017394-ページ-97.pdf"
    }
  ]
}